{"attempts":39,"baselines":["duckdb-raw","gzip-6","jsonl","parquet-raw-zstd","tracefold-auto-zstd9","tracefold-separate-zstd1","tracefold-separate-zstd3","tracefold-separate-zstd9","tracefold-unified-zstd3","tracefold-unified-zstd9","views-parquet-zstd","zstd-3","zstd-9"],"charts":["archive-bytes.svg","compression-ratio.svg","pareto.svg","encode-throughput.svg","peak-rss.svg","retention-frontier.svg","bucket-frontier.svg","scale-cardinality.svg","error-retention.svg","format-ablation.svg","failures.svg"],"datasets":["loghub-bgl","loghub-zookeeper","smoke-standard-10000"],"diagrams":["encoding-pipeline.svg","query-path.svg","retention-contract.svg"],"failed_attempts":0,"failures":[],"illegal_queries_per_archive":20,"largest_normalized_bytes":2004094557,"largest_observed_source_bytes":57489019,"legal_queries_per_archive":200,"max_source_bytes":1073741824,"schema_version":1,"semantic_mismatch_count":0,"snapshot_id":"6666bcc18a5b6627da0824ac3e5536aa95287e538653f16ea89b7973e17dc937","successful_attempts":39,"table":[{"archive_bytes_median":342896640.0,"attempts":1,"baseline":"duckdb-raw","compression_ratio_median":5.844602493042801,"dataset":"loghub-bgl","encode_wall_ns_median":8873726551.0,"encode_wall_ns_p95":8873726551.0,"query_wall_ns_median":8755092617.0},{"archive_bytes_median":95423564.0,"attempts":1,"baseline":"gzip-6","compression_ratio_median":21.00209291071962,"dataset":"loghub-bgl","encode_wall_ns_median":7701684685.0,"encode_wall_ns_p95":7701684685.0,"query_wall_ns_median":9431680956.0},{"archive_bytes_median":2004094557.0,"attempts":1,"baseline":"jsonl","compression_ratio_median":1.0,"dataset":"loghub-bgl","encode_wall_ns_median":800.0,"encode_wall_ns_p95":800.0,"query_wall_ns_median":9074821672.0},{"archive_bytes_median":80953926.0,"attempts":1,"baseline":"parquet-raw-zstd","compression_ratio_median":24.75598968479923,"dataset":"loghub-bgl","encode_wall_ns_median":2171080882.0,"encode_wall_ns_p95":2171080882.0,"query_wall_ns_median":8992310769.0},{"archive_bytes_median":4698677.0,"attempts":1,"baseline":"tracefold-auto-zstd9","compression_ratio_median":426.52315896581104,"dataset":"loghub-bgl","encode_wall_ns_median":47051453119.0,"encode_wall_ns_p95":47051453119.0,"query_wall_ns_median":2593739486.0},{"archive_bytes_median":6426634.0,"attempts":1,"baseline":"views-parquet-zstd","compression_ratio_median":311.8420244563484,"dataset":"loghub-bgl","encode_wall_ns_median":651705719.0,"encode_wall_ns_p95":651705719.0,"query_wall_ns_median":10041476198.0},{"archive_bytes_median":100358115.0,"attempts":1,"baseline":"zstd-3","compression_ratio_median":19.969432038455484,"dataset":"loghub-bgl","encode_wall_ns_median":2587710799.0,"encode_wall_ns_p95":2587710799.0,"query_wall_ns_median":9384315504.0},{"archive_bytes_median":73285895.0,"attempts":1,"baseline":"zstd-9","compression_ratio_median":27.346252058462273,"dataset":"loghub-bgl","encode_wall_ns_median":14023699355.0,"encode_wall_ns_p95":14023699355.0,"query_wall_ns_median":9541499576.0},{"archive_bytes_median":5517312.0,"attempts":1,"baseline":"duckdb-raw","compression_ratio_median":5.3936855483249815,"dataset":"loghub-zookeeper","encode_wall_ns_median":339171401.0,"encode_wall_ns_p95":339171401.0,"query_wall_ns_median":2965184915.0},{"archive_bytes_median":939710.0,"attempts":1,"baseline":"gzip-6","compression_ratio_median":31.667903927807515,"dataset":"loghub-zookeeper","encode_wall_ns_median":82110990.0,"encode_wall_ns_p95":82110990.0,"query_wall_ns_median":422073881.0},{"archive_bytes_median":29758646.0,"attempts":1,"baseline":"jsonl","compression_ratio_median":1.0,"dataset":"loghub-zookeeper","encode_wall_ns_median":1000.0,"encode_wall_ns_p95":1000.0,"query_wall_ns_median":416824375.0},{"archive_bytes_median":642771.0,"attempts":1,"baseline":"parquet-raw-zstd","compression_ratio_median":46.297430966860674,"dataset":"loghub-zookeeper","encode_wall_ns_median":64419639.0,"encode_wall_ns_p95":64419639.0,"query_wall_ns_median":3121737848.0},{"archive_bytes_median":53964.0,"attempts":1,"baseline":"tracefold-auto-zstd9","compression_ratio_median":551.4536728189163,"dataset":"loghub-zookeeper","encode_wall_ns_median":727508962.0,"encode_wall_ns_p95":727508962.0,"query_wall_ns_median":841489106.0},{"archive_bytes_median":210671.0,"attempts":1,"baseline":"views-parquet-zstd","compression_ratio_median":141.25648997726313,"dataset":"loghub-zookeeper","encode_wall_ns_median":106770189.0,"encode_wall_ns_p95":106770189.0,"query_wall_ns_median":3292329435.0},{"archive_bytes_median":978507.0,"attempts":1,"baseline":"zstd-3","compression_ratio_median":30.41229751039083,"dataset":"loghub-zookeeper","encode_wall_ns_median":31549180.0,"encode_wall_ns_p95":31549180.0,"query_wall_ns_median":419163941.0},{"archive_bytes_median":693507.0,"attempts":1,"baseline":"zstd-9","compression_ratio_median":42.91037581451953,"dataset":"loghub-zookeeper","encode_wall_ns_median":176392827.0,"encode_wall_ns_p95":176392827.0,"query_wall_ns_median":426532828.0},{"archive_bytes_median":798720.0,"attempts":1,"baseline":"duckdb-raw","compression_ratio_median":5.806281300080128,"dataset":"smoke-standard-10000","encode_wall_ns_median":144323430.0,"encode_wall_ns_p95":144323430.0,"query_wall_ns_median":1478434030.0},{"archive_bytes_median":459351.0,"attempts":1,"baseline":"gzip-6","compression_ratio_median":10.095968007036014,"dataset":"smoke-standard-10000","encode_wall_ns_median":45329937.0,"encode_wall_ns_p95":45329937.0,"query_wall_ns_median":206864528.0},{"archive_bytes_median":4637593.0,"attempts":1,"baseline":"jsonl","compression_ratio_median":1.0,"dataset":"smoke-standard-10000","encode_wall_ns_median":700.0,"encode_wall_ns_p95":700.0,"query_wall_ns_median":205081923.0},{"archive_bytes_median":250620.0,"attempts":1,"baseline":"parquet-raw-zstd","compression_ratio_median":18.50448088739925,"dataset":"smoke-standard-10000","encode_wall_ns_median":12385466.0,"encode_wall_ns_p95":12385466.0,"query_wall_ns_median":1542514677.0},{"archive_bytes_median":218127.0,"attempts":1,"baseline":"tracefold-auto-zstd9","compression_ratio_median":21.26097640365475,"dataset":"smoke-standard-10000","encode_wall_ns_median":360293062.0,"encode_wall_ns_p95":360293062.0,"query_wall_ns_median":810707511.0},{"archive_bytes_median":1377243.0,"attempts":1,"baseline":"views-parquet-zstd","compression_ratio_median":3.3673019213021957,"dataset":"smoke-standard-10000","encode_wall_ns_median":76464822.0,"encode_wall_ns_p95":76464822.0,"query_wall_ns_median":1695591942.0},{"archive_bytes_median":456689.0,"attempts":1,"baseline":"zstd-3","compression_ratio_median":10.154816516272561,"dataset":"smoke-standard-10000","encode_wall_ns_median":15881688.0,"encode_wall_ns_p95":15881688.0,"query_wall_ns_median":209219318.0},{"archive_bytes_median":390177.0,"attempts":1,"baseline":"zstd-9","compression_ratio_median":11.885869746294631,"dataset":"smoke-standard-10000","encode_wall_ns_median":65368974.0,"encode_wall_ns_p95":65368974.0,"query_wall_ns_median":205243264.0}]}
